_breakout_detection.cpython-35m-x86_64-linux-gnu.so
breakout_detection_lolinternet-0.1.dist-info/WHEEL
breakout_detection_lolinternet-0.1.dist-info/RECORD
breakout_detection_lolinternet-0.1.dist-info/top_level.txt
breakout_detection_lolinternet-0.1.dist-info/METADATA
