Metadata-Version: 2.1
Name: breakout-detection-lolinternet
Version: 0.1
Summary: Breakout Detection
Home-page: UNKNOWN
Author: UNKNOWN
Author-email: UNKNOWN
License: UNKNOWN
Platform: UNKNOWN
